Metadata-Version: 1.1
Name: xxurl
Version: 0.4
Summary: handle url, javascript-style APIs
Home-page: https://github.com/ihgazni2/xxurl
Author: dapeli
Author-email: terryinzaghi@163.com
License: MIT
Platform: UNKNOWN
Classifier: Environment :: Console
Classifier: Environment :: Web Environment
Classifier: Intended Audience :: End Users/Desktop
Classifier: Intended Audience :: Developers
Classifier: Intended Audience :: System Administrators
Classifier: Programming Language :: Python
